<?xml version='1.0' encoding='utf-8'?>
<TextureAtlas imagePath="Bambi_ChillingWithTheCorn.png">
	
	
	<SubTexture name="cool0000" x="0" y="0" width="63" height="70" />
	<SubTexture name="cool0001" x="0" y="0" width="63" height="70" />
	<SubTexture name="cool0002" x="64" y="0" width="63" height="70" />
	<SubTexture name="cool0003" x="64" y="0" width="63" height="70" />
	<SubTexture name="cool0004" x="128" y="0" width="63" height="70" />
	<SubTexture name="cool0005" x="128" y="0" width="63" height="70" />
	<SubTexture name="cool0006" x="192" y="0" width="63" height="70" />
	<SubTexture name="cool0007" x="192" y="0" width="63" height="70" />
</TextureAtlas>